pyencrypto/__init__.py
pyencrypto/crypter/__init__.py
pyencrypto/crypter/crypter.py
pyencrypto/crypter/exceptions.py
pyencrypto-1.0.dist-info/METADATA
pyencrypto-1.0.dist-info/WHEEL
pyencrypto-1.0.dist-info/top_level.txt
pyencrypto-1.0.dist-info/RECORD
